megatechai/__init__.py
megatechai/examples/__init__.py
megatechai/megatechai/examples/model_api_example.cpython-312-x86_64-linux-gnu.so
megatechai/megatechai/model_api/api.cpython-312-x86_64-linux-gnu.so
megatechai/megatechai/model_api/mega_params.cpython-312-x86_64-linux-gnu.so
megatechai/megatechai/model_api/params.cpython-312-x86_64-linux-gnu.so
megatechai/megatechai/utils/http_client.cpython-312-x86_64-linux-gnu.so
megatechai/megatechai/utils/jwt_token.cpython-312-x86_64-linux-gnu.so
megatechai/megatechai/utils/sse_client.cpython-312-x86_64-linux-gnu.so
megatechai/model_api/__init__.py
megatechai/utils/__init__.py
megatechai-2.1.1.dist-info/LICENSE
megatechai-2.1.1.dist-info/METADATA
megatechai-2.1.1.dist-info/WHEEL
megatechai-2.1.1.dist-info/top_level.txt
megatechai-2.1.1.dist-info/RECORD
