Metadata-Version: 2.1
Name: megatechai
Version: 2.1.1
Summary: llm sdk
Home-page: https://megatechai.com
Author: MegatechAI
Author-email: huoshuai@megatechai.com
Classifier: Programming Language :: Python :: 3
Classifier: License :: OSI Approved :: MIT License
Classifier: Operating System :: OS Independent
License-File: LICENSE
